le_utils/__init__.py
le_utils/humanhash.py
le_utils/proquint.py
le_utils/constants/__init__.py
le_utils/constants/content_kinds.py
le_utils/constants/exercises.py
le_utils/constants/file_formats.py
le_utils/constants/file_types.py
le_utils/constants/format_presets.py
le_utils/constants/languages.py
le_utils/constants/licenses.py
le_utils/constants/roles.py
le_utils/constants/labels/__init__.py
le_utils/constants/labels/accessibility_categories.py
le_utils/constants/labels/learning_activities.py
le_utils/constants/labels/levels.py
le_utils/constants/labels/needs.py
le_utils/constants/labels/resource_type.py
le_utils/constants/labels/subjects.py
le_utils/resources/formatlookup.json
le_utils/resources/kindlookup.json
le_utils/resources/languagelookup.json
le_utils/resources/licenselookup.json
le_utils/resources/presetlookup.json
le_utils-0.1.33.dist-info/LICENSE.txt
le_utils-0.1.33.dist-info/METADATA
le_utils-0.1.33.dist-info/WHEEL
le_utils-0.1.33.dist-info/top_level.txt
le_utils-0.1.33.dist-info/RECORD
