Metadata-Version: 2.1
Name: le-utils
Version: 0.1.33
Summary: LE-Utils contains shared constants used in Kolibri, Ricecooker, and Kolibri Studio.
Home-page: https://github.com/learningequality/le-utils
Author: Learning Equality
Author-email: info@learningequality.org
License: MIT
Download-URL: https://github.com/learningequality/le-utils/releases
Keywords: le-utils le_utils LE utils kolibri studio ricecooker content curation
Platform: UNKNOWN
Classifier: Development Status :: 2 - Pre-Alpha
Classifier: Programming Language :: Python
Classifier: License :: OSI Approved :: MIT License
Classifier: Topic :: Utilities
Requires-Dist: pycountry (==17.5.14)
